pelican/plugins/markdown_it_reader/__init__.py
pelican/plugins/markdown_it_reader/markdown_it_reader.py
pelican/plugins/markdown_it_reader/test_markdown_it_reader.py
pelican_markdown_it_reader-2.0.4.dist-info/METADATA
pelican_markdown_it_reader-2.0.4.dist-info/WHEEL
pelican_markdown_it_reader-2.0.4.dist-info/RECORD
