Metadata-Version: 2.4
Name: pelican-markdown-it-reader
Version: 2.0.4
Summary: Reader plugin for Markdown-IT-py replacement
License: MIT
Keywords: pelican,plugin
Author: Gaige B. Paulsen
Author-email: gaige@cluetrust.com
Requires-Python: >=3.8,<4.0
Classifier: Development Status :: 5 - Production/Stable
Classifier: Environment :: Plugins
Classifier: Framework :: Pelican
Classifier: Framework :: Pelican :: Plugins
Classifier: Intended Audience :: End Users/Desktop
Classifier: License :: OSI Approved :: MIT License
Classifier: Operating System :: OS Independent
Classifier: Programming Language :: Python :: 3
Classifier: Programming Language :: Python :: 3.8
Classifier: Programming Language :: Python :: 3.9
Classifier: Programming Language :: Python :: 3.10
Classifier: Programming Language :: Python :: 3.11
Classifier: Programming Language :: Python :: 3.12
Classifier: Programming Language :: Python :: 3.13
Classifier: Programming Language :: Python :: 3.14
Classifier: Topic :: Internet :: WWW/HTTP
Classifier: Topic :: Software Development :: Libraries :: Python Modules
Provides-Extra: markdown
Requires-Dist: Pygments (>=2.6,<3.0)
Requires-Dist: markdown (>=3.2.2,<4.0.0) ; extra == "markdown"
Requires-Dist: markdown-it-py (>=1.1,<4.0)
Requires-Dist: mdit-py-plugins (>=0.2.8,<0.5.0)
Requires-Dist: pelican (>=4.5)
Project-URL: Documentation, https://docs.getpelican.com
Project-URL: Issue Tracker, https://github.com/gaige/markdown-it-reader/issues
Project-URL: Repository, https://github.com/gaige/markdown-it-reader
